orion/__init__.py
orion/biolink_constants.py
orion/biolink_utils.py
orion/build_manager.py
orion/collapse_qualifiers.py
orion/config.py
orion/containers.py
orion/data_sources.py
orion/db_connectors.py
orion/exceptions.py
orion/extractor.py
orion/hgvs_utils.py
orion/kgx_file_converter.py
orion/kgx_file_merger.py
orion/kgx_file_normalizer.py
orion/kgx_file_writer.py
orion/kgx_metadata.py
orion/kgx_validation.py
orion/kgxmodel.py
orion/load_manager.py
orion/loader_interface.py
orion/memgraph_tools.py
orion/merging.py
orion/meta_kg.py
orion/metadata.py
orion/neo4j_meta_kg.py
orion/neo4j_tools.py
orion/normalization.py
orion/predicates.py
orion/prefixes.py
orion/redundant_kg.py
orion/supplementation.py
orion/utils.py
robokop_orion-0.1.14.dist-info/licenses/LICENSE
robokop_orion-0.1.14.dist-info/WHEEL
robokop_orion-0.1.14.dist-info/METADATA
robokop_orion-0.1.14.dist-info/RECORD
