Metadata-Version: 2.4
Name: robokop-orion
Version: 0.1.14
Summary: ORION ingests data from knowledge sources and converts them into interoperable biolink model compliant knowledge graphs.
License-Expression: MIT
License-File: LICENSE
Requires-Dist: bmt>=1.4.6
Requires-Dist: jsonlines>=4.0.0
Requires-Dist: orjson>=3.11.3
Requires-Dist: python-dotenv>=1.0.1
Requires-Dist: pyyaml>=6.0.1
Requires-Dist: requests>=2.32.5
Requires-Dist: requests-toolbelt>=1.0.0
Requires-Dist: robokop-genetics>=0.7.0
Requires-Dist: xxhash>=3.6.0
Requires-Dist: curies>=0.7.9 ; extra == 'robokop'
Requires-Dist: redis>=5.2.1 ; extra == 'robokop'
Requires-Dist: psycopg2-binary>=2.9.9 ; extra == 'robokop'
Requires-Dist: pyoxigraph>=0.3.22 ; extra == 'robokop'
Requires-Dist: beautifulsoup4>=4.12.3 ; extra == 'robokop'
Requires-Dist: celery>=5.4.0 ; extra == 'robokop'
Requires-Dist: intermine ; extra == 'robokop'
Requires-Dist: mysql-connector-python>=9.4.0 ; extra == 'robokop'
Requires-Dist: neo4j>=5.28.0 ; extra == 'robokop'
Requires-Dist: openpyxl>=3.1.5 ; extra == 'robokop'
Requires-Dist: pandas>=2.3.3 ; extra == 'robokop'
Requires-Dist: polars>=1.19.0 ; extra == 'robokop'
Requires-Dist: prefixmaps>=0.2.6 ; extra == 'robokop'
Requires-Dist: pytest>=8.4.2 ; extra == 'robokop'
Requires-Python: >=3.12
Provides-Extra: robokop
